nvidia/cu13/include/cuda_stdint.h
nvidia/cu13/include/cupti.h
nvidia/cu13/include/cupti_activity.h
nvidia/cu13/include/cupti_activity_deprecated.h
nvidia/cu13/include/cupti_callbacks.h
nvidia/cu13/include/cupti_checkpoint.h
nvidia/cu13/include/cupti_common.h
nvidia/cu13/include/cupti_driver_cbid.h
nvidia/cu13/include/cupti_events.h
nvidia/cu13/include/cupti_metrics.h
nvidia/cu13/include/cupti_nvtx_cbid.h
nvidia/cu13/include/cupti_pcsampling.h
nvidia/cu13/include/cupti_pcsampling_util.h
nvidia/cu13/include/cupti_pmsampling.h
nvidia/cu13/include/cupti_profiler_host.h
nvidia/cu13/include/cupti_profiler_target.h
nvidia/cu13/include/cupti_range_profiler.h
nvidia/cu13/include/cupti_result.h
nvidia/cu13/include/cupti_runtime_cbid.h
nvidia/cu13/include/cupti_sass_metrics.h
nvidia/cu13/include/cupti_target.h
nvidia/cu13/include/cupti_version.h
nvidia/cu13/include/generated_cudaGL_meta.h
nvidia/cu13/include/generated_cudaVDPAU_meta.h
nvidia/cu13/include/generated_cuda_gl_interop_meta.h
nvidia/cu13/include/generated_cuda_meta.h
nvidia/cu13/include/generated_cuda_runtime_api_meta.h
nvidia/cu13/include/generated_cuda_vdpau_interop_meta.h
nvidia/cu13/include/generated_cudart_removed_meta.h
nvidia/cu13/include/generated_nvtx_meta.h
nvidia/cu13/include/nvperf_common.h
nvidia/cu13/include/nvperf_cuda_host.h
nvidia/cu13/include/nvperf_host.h
nvidia/cu13/include/nvperf_target.h
nvidia/cu13/include/Openacc/cupti_openacc.h
nvidia/cu13/include/Openmp/cupti_openmp.h
nvidia/cu13/include/Openmp/omp-tools.h
nvidia/cu13/lib/libcheckpoint.so
nvidia/cu13/lib/libcupti.so.13
nvidia/cu13/lib/libnvperf_host.so
nvidia/cu13/lib/libnvperf_target.so
nvidia/cu13/lib/libpcsamplingutil.so
nvidia_cuda_cupti-13.1.75.dist-info/licenses/License.txt
nvidia_cuda_cupti-13.1.75.dist-info/METADATA
nvidia_cuda_cupti-13.1.75.dist-info/WHEEL
nvidia_cuda_cupti-13.1.75.dist-info/top_level.txt
nvidia_cuda_cupti-13.1.75.dist-info/RECORD
